{
	"addonId": "agenda",
	"displayName": "Accessible agenda",
	"URL": "https://github.com/ruifontes/agenda-for-NVDA/releases/download/2026.05.14/agenda-2026.05.14.nvda-addon",
	"description": "Allows access to an accesible agenda",
	"sha256": "226fb0dec7698023ba4f643947c2dcc20f2c972fbf65c4d82d994db8753d9ef8",
	"addonVersionName": "2026.05.14",
	"addonVersionNumber": {
		"major": 2026,
		"minor": 5,
		"patch": 14
	},
	"minNVDAVersion": {
		"major": 2019,
		"minor": 3,
		"patch": 0
	},
	"lastTestedVersion": {
		"major": 2026,
		"minor": 1,
		"patch": 0
	},
	"channel": "stable",
	"publisher": "Rui Fontes",
	"sourceURL": "https://github.com/ruifontes/agenda-for-NVDA",
	"license": "GPL v2",
	"homepage": "https://github.com/ruifontes/agenda-for-NVDA",
	"changelog": "Corrected a bug preventing to open the main window in certain cases.",
	"licenseURL": "https://www.gnu.org/licenses/gpl-2.0.html",
	"submissionTime": 1778714667000,
	"translations": [
		{
			"language": "en",
			"displayName": "Accessible agenda",
			"description": "Allows access to an accesible agenda",
			"changelog": "Corrected a bug preventing to open the main window in certain cases."
		},
		{
			"language": "es",
			"displayName": "Agenda accesible",
			"description": "Permite acceder a una agenda accesible",
			"changelog": "Corrected a bug preventing to open the main window in certain cases."
		},
		{
			"language": "fa",
			"displayName": "سررسیدِ دسترسپذیر",
			"description": "اجازه میدهد به یک سررسیدِ دسترسپذیر دست یابید",
			"changelog": "Corrected a bug preventing to open the main window in certain cases."
		},
		{
			"language": "fi",
			"displayName": "Esteetön asialista",
			"description": "Mahdollistaa pääsyn esteettömään esityslistaan",
			"changelog": "Corrected a bug preventing to open the main window in certain cases."
		},
		{
			"language": "fr",
			"displayName": "Agenda accessible",
			"description": "Permet d'accéder à une agenda accessible",
			"changelog": "Corrected a bug preventing to open the main window in certain cases."
		},
		{
			"language": "pt_BR",
			"displayName": "Agenda acessível",
			"description": "Permite utilizar uma agenda acessível",
			"changelog": "Corrected a bug preventing to open the main window in certain cases."
		},
		{
			"language": "pt_PT",
			"displayName": "Agenda acessível",
			"description": "Permite o acesso a uma agenda acessível",
			"changelog": "Corrected a bug preventing to open the main window in certain cases."
		},
		{
			"language": "tr",
			"displayName": "Erişilebilir Ajanda",
			"description": "Erişilebilir bir ajandaya erişim sağlar",
			"changelog": "Corrected a bug preventing to open the main window in certain cases."
		},
		{
			"language": "uk",
			"displayName": "Доступний порядок денний",
			"description": "Надає доступ до доступного порядку денного",
			"changelog": "Corrected a bug preventing to open the main window in certain cases."
		}
	],
	"vtScanUrl": "https://www.virustotal.com/gui/file/226fb0dec7698023ba4f643947c2dcc20f2c972fbf65c4d82d994db8753d9ef8",
	"scanResults": {
		"virusTotal": [
			{
				"_id": "226fb0dec7698023ba4f643947c2dcc20f2c972fbf65c4d82d994db8753d9ef8",
				"_type": "file",
				"filecondis": {
					"dhash": "000000000e070600",
					"raw_md5": "751a7140c08dd5de066c85d2ac7ab49d"
				},
				"first_submission_date": 1778714687,
				"last_analysis_results": {},
				"last_analysis_stats": {
					"confirmed-timeout": 0,
					"failure": 0,
					"harmless": 0,
					"malicious": 0,
					"suspicious": 0,
					"timeout": 0,
					"type-unsupported": 0,
					"undetected": 0
				},
				"last_modification_date": 1778714688,
				"last_submission_date": 1778714687,
				"md5": "ec4f6fa970abd639b033fc1ed8ebcac6",
				"names": [],
				"reputation": 0,
				"sha1": "5514de32da3dce0097b31417b697e89ef7912e27",
				"sha256": "226fb0dec7698023ba4f643947c2dcc20f2c972fbf65c4d82d994db8753d9ef8",
				"size": 8972521,
				"tags": [],
				"times_submitted": 1,
				"total_votes": {
					"harmless": 0,
					"malicious": 0
				},
				"type_description": "unknown",
				"type_tags": [],
				"unique_sources": 1
			}
		]
	},
	"reviewUrl": "https://github.com/nvaccess/addon-datastore/discussions/2307"
}
